tree_sitter_commonlisp/__init__.py
tree_sitter_commonlisp/__init__.pyi
tree_sitter_commonlisp/_binding.abi3.so
tree_sitter_commonlisp/binding.c
tree_sitter_commonlisp/py.typed
tree_sitter_commonlisp/queries/tags.scm
tree_sitter_commonlisp-0.4.1.dist-info/LICENSE.md
tree_sitter_commonlisp-0.4.1.dist-info/METADATA
tree_sitter_commonlisp-0.4.1.dist-info/WHEEL
tree_sitter_commonlisp-0.4.1.dist-info/top_level.txt
tree_sitter_commonlisp-0.4.1.dist-info/RECORD
