Metadata-Version: 2.2
Name: tree-sitter-commonlisp
Version: 0.4.1
Summary: Commonlisp grammar for tree-sitter
License: MIT
Project-URL: Homepage, https://github.com/tree-sitter-grammars/tree-sitter-commonlisp
Keywords: incremental,parsing,tree-sitter,commonlisp
Classifier: Intended Audience :: Developers
Classifier: License :: OSI Approved :: MIT License
Classifier: Topic :: Software Development :: Compilers
Classifier: Topic :: Text Processing :: Linguistic
Classifier: Typing :: Typed
Requires-Python: >=3.9
License-File: LICENSE.md
Provides-Extra: core
Requires-Dist: tree-sitter~=0.21; extra == "core"
